cheryl_my_package/__init__.py
cheryl_my_package/cli.py
cheryl_my_package/core.py
cheryl_my_package/utils.py
cheryl_my_package-0.1.3.dist-info/METADATA
cheryl_my_package-0.1.3.dist-info/WHEEL
cheryl_my_package-0.1.3.dist-info/licenses/LICENSE
cheryl_my_package-0.1.3.dist-info/RECORD
